tornado/options.py
tornado/ioloop.py
tornado/web.py
tornado/autoreload.py
tornado/speedups.abi3.so
tornado/httpclient.py
tornado/websocket.py
tornado/curl_httpclient.py
tornado/locale.py
tornado/httpserver.py
tornado/escape.py
tornado/py.typed
tornado/testing.py
tornado/wsgi.py
tornado/httputil.py
tornado/iostream.py
tornado/__init__.pyi
tornado/locks.py
tornado/log.py
tornado/tcpserver.py
tornado/util.py
tornado/speedups.pyi
tornado/concurrent.py
tornado/tcpclient.py
tornado/queues.py
tornado/process.py
tornado/routing.py
tornado/_locale_data.py
tornado/http1connection.py
tornado/__init__.py
tornado/netutil.py
tornado/gen.py
tornado/auth.py
tornado/template.py
tornado/simple_httpclient.py
tornado/test/options_test.py
tornado/test/wsgi_test.py
tornado/test/gen_test.py
tornado/test/twisted_test.py
tornado/test/http1connection_test.py
tornado/test/tcpserver_test.py
tornado/test/simple_httpclient_test.py
tornado/test/log_test.py
tornado/test/iostream_test.py
tornado/test/util_test.py
tornado/test/options_test.cfg
tornado/test/netutil_test.py
tornado/test/test.crt
tornado/test/web_test.py
tornado/test/autoreload_test.py
tornado/test/template_test.py
tornado/test/test.key
tornado/test/circlerefs_test.py
tornado/test/options_test_types.cfg
tornado/test/escape_test.py
tornado/test/static_foo.txt
tornado/test/routing_test.py
tornado/test/httputil_test.py
tornado/test/locks_test.py
tornado/test/httpclient_test.py
tornado/test/__main__.py
tornado/test/resolve_test_helper.py
tornado/test/websocket_test.py
tornado/test/httpserver_test.py
tornado/test/util.py
tornado/test/options_test_types_str.cfg
tornado/test/import_test.py
tornado/test/auth_test.py
tornado/test/asyncio_test.py
tornado/test/concurrent_test.py
tornado/test/curl_httpclient_test.py
tornado/test/tcpclient_test.py
tornado/test/runtests.py
tornado/test/queues_test.py
tornado/test/__init__.py
tornado/test/locale_test.py
tornado-6.5.dist-info/METADATA
tornado-6.5.dist-info/WHEEL
tornado-6.5.dist-info/RECORD
tornado-6.5.dist-info/top_level.txt
tornado-6.5.dist-info/licenses/LICENSE
