Metadata-Version: 2.1
Name: tornado
Version: 6.5
Summary: Tornado is a Python web framework and asynchronous networking library, originally developed at FriendFeed.
Home-page: http://www.tornadoweb.org/
Author: Facebook
Author-email: python-tornado@googlegroups.com
License: Apache-2.0
Project-URL: Source, https://github.com/tornadoweb/tornado
Platform: UNKNOWN
Classifier: License :: OSI Approved :: Apache Software License
Classifier: Programming Language :: Python :: 3
Classifier: Programming Language :: Python :: 3.9
Classifier: Programming Language :: Python :: 3.10
Classifier: Programming Language :: Python :: 3.11
Classifier: Programming Language :: Python :: 3.12
Classifier: Programming Language :: Python :: 3.13
Classifier: Programming Language :: Python :: Implementation :: CPython
Classifier: Programming Language :: Python :: Implementation :: PyPy
Requires-Python: >= 3.9
License-File: LICENSE
